aioga/__init__.py
aioga-0.1.0.dist-info/METADATA
aioga-0.1.0.dist-info/RECORD
aioga-0.1.0.dist-info/WHEEL
aioga-0.1.0.dist-info/top_level.txt
