Metadata-Version: 2.1
Name: aioga
Version: 0.1.0
Summary: Google Analytics client for asyncio
Home-page: https://github.com/aio-libs/aioga
Author: wikibusiness
Author-email: osf@wikibusiness.org
License: UNKNOWN
Keywords: google analytics,measurement protocol,asyncio,aiohttp
Platform: UNKNOWN
Classifier: Development Status :: 5 - Production/Stable
Classifier: Intended Audience :: Developers
Classifier: License :: OSI Approved :: MIT License
Classifier: Operating System :: POSIX
Classifier: Operating System :: MacOS :: MacOS X
Classifier: Operating System :: Microsoft :: Windows
Classifier: Programming Language :: Python
Classifier: Programming Language :: Python :: 3
Classifier: Programming Language :: Python :: 3.5
Classifier: Programming Language :: Python :: 3.6
Requires-Python: >=3.5.3
Requires-Dist: aiohttp (>=3.0.0)
Requires-Dist: async-timeout
Requires-Dist: yarl
